{
  "name": "oracle-demo",
  "workflows": {
    "compute_median": {
      "trigger": {
        "stellar_contract_event": {
          "chain": "stellar:testnet",
          "contract_id": "CCAHDNNFL7H2YGMGGPUV6OHGF3YNXNMRRFPUZJZTEV3LKOBIRGB3U2KQ",
          "topic_segments": [
            {
              "exact": {
                "symbol": "r2ready"
              }
            },
            "wildcard"
          ]
        }
      },
      "component": {
        "source": {
          "digest": "291d44c21b58d133aea689967a27294f577dc1827ea24b6e50cfeff117a9b838"
        },
        "permissions": {
          "allowed_http_hosts": "none",
          "file_system": false,
          "raw_sockets": false,
          "dns_resolution": false
        },
        "fuel_limit": null,
        "time_limit_seconds": null,
        "config": {},
        "env_keys": []
      },
      "submit": {
        "aggregator": {
          "component": {
            "source": {
              "digest": "8ee77ea28f9834d579f51c43a58c4719297139b2ec7dd7a930def064d0832775"
            },
            "permissions": {
              "allowed_http_hosts": "none",
              "file_system": false,
              "raw_sockets": false,
              "dns_resolution": false
            },
            "fuel_limit": null,
            "time_limit_seconds": null,
            "config": {
              "chain": "stellar:testnet",
              "service_handler": "CCAHDNNFL7H2YGMGGPUV6OHGF3YNXNMRRFPUZJZTEV3LKOBIRGB3U2KQ"
            },
            "env_keys": []
          }
        }
      }
    },
    "compute_twap": {
      "trigger": {
        "stellar_contract_event": {
          "chain": "stellar:testnet",
          "contract_id": "CCAHDNNFL7H2YGMGGPUV6OHGF3YNXNMRRFPUZJZTEV3LKOBIRGB3U2KQ",
          "topic_segments": [
            {
              "exact": {
                "symbol": "twapreq"
              }
            },
            "wildcard"
          ]
        }
      },
      "component": {
        "source": {
          "digest": "eb80c382d6f94d9cbc616948b98e15c7003be848147ca684ea922bfa0496f23e"
        },
        "permissions": {
          "allowed_http_hosts": "none",
          "file_system": false,
          "raw_sockets": false,
          "dns_resolution": false
        },
        "fuel_limit": null,
        "time_limit_seconds": null,
        "config": {},
        "env_keys": []
      },
      "submit": {
        "aggregator": {
          "component": {
            "source": {
              "digest": "8ee77ea28f9834d579f51c43a58c4719297139b2ec7dd7a930def064d0832775"
            },
            "permissions": {
              "allowed_http_hosts": "none",
              "file_system": false,
              "raw_sockets": false,
              "dns_resolution": false
            },
            "fuel_limit": null,
            "time_limit_seconds": null,
            "config": {
              "chain": "stellar:testnet",
              "service_handler": "CCAHDNNFL7H2YGMGGPUV6OHGF3YNXNMRRFPUZJZTEV3LKOBIRGB3U2KQ"
            },
            "env_keys": []
          }
        }
      }
    },
    "fetch_prices": {
      "trigger": {
        "cron": {
          "schedule": "*/30 * * * * *",
          "start_time": null,
          "end_time": null
        }
      },
      "component": {
        "source": {
          "digest": "f0912f363fee2ec849f0f2964807a316623d4694d6c5c3f059c66caa2e901b69"
        },
        "permissions": {
          "allowed_http_hosts": {
            "only": [
              "api.coingecko.com",
              "pro-api.coingecko.com"
            ]
          },
          "file_system": false,
          "raw_sockets": false,
          "dns_resolution": false
        },
        "fuel_limit": null,
        "time_limit_seconds": null,
        "config": {},
        "env_keys": []
      },
      "submit": "none"
    }
  },
  "status": "active",
  "manager": {
    "stellar": {
      "chain": "stellar:testnet",
      "address": "CCS76IZNINQRO2OO2HR2HJRGRIBT6VQB4EYKNSEUIMHMEEF67TD7ZXG4"
    }
  },
  "signature_kind": {
    "algorithm": "ed25519",
    "prefix": "sep53"
  }
}
